{
  "title": "The Role of Virtual Reality in Enhancing Vanilla Hytale Server Experiences in 2026",
  "excerpt": "Explore how virtual reality is transforming vanilla Hytale server gameplay, offering immersive experiences that redefine player interaction and creativity in 2026.",
  "content": "Virtual reality (VR) is no longer a futuristic concept—it's a transformative tool redefining how we interact with digital worlds. In 2026, VR plays a critical role in enhancing the vanilla Hytale server experience, offering players an immersive gateway to creativity and community like never before.\n\n## The Integration of VR in Hytale\n\nHytale, known for its sandbox mechanics and vibrant community, has embraced VR to push the boundaries of player engagement. By integrating VR technology, vanilla servers now offer a more tactile, immersive experience. Players can:\n\n- **Explore Landscapes**: Traverse the diverse biomes of Hytale in a fully immersive VR environment, where every mountain, forest, and cave feels life-sized and tangible.\n- **Build with Precision**: Utilize hand-tracking and intuitive VR controls to construct complex structures with unprecedented precision and ease.\n- **Engage in Combat**: Experience heart-pounding battles with realistic weapon handling and movement, bringing a new level of immersion to combat scenarios.\n\n## Benefits of VR in Vanilla Hytale Servers\n\n### Enhanced Creativity\n\nWith VR, players can manipulate the environment in three dimensions, leading to more innovative and creative building techniques. This spatial awareness allows for more intricate designs and architectural marvels.\n\n### Improved Social Interaction\n\nVirtual reality fosters a sense of presence that traditional screens cannot match. Players on vanilla servers can:\n\n- **Communicate in Real-Time**: Use voice and gestures to interact with friends, making collaborations more dynamic and engaging.\n- **Host Virtual Events**: Organize and attend events such as concerts or community meetings in a fully immersive digital space.\n\n### Immersive Gameplay\n\nVR enhances the sensory experience, making every adventure in Hytale more engaging. Whether it's feeling the thrill of exploration or the tension of combat, VR amplifies emotional and physical responses.\n\n## Challenges and Considerations\n\n### Technical Requirements\n\nTo fully enjoy VR in Hytale, players need powerful hardware capable of running both the game and VR software smoothly. This requirement can be a barrier for some, but technological advancements continue to make VR more accessible.\n\n### Motion Sickness\n\nSome players may experience discomfort or motion sickness in VR environments. Developers are actively working on solutions, such as improved frame rates and motion controls, to minimize these issues.\n\n## The Future of VR in Hytale\n\nAs we move forward, the future of VR in Hytale looks promising. Continued advancements in VR technology will likely lead to:\n\n- **More Accessible VR Gear**: As VR headsets become more affordable and user-friendly, a broader range of players will be able to experience VR-enhanced gameplay.\n- **Evolving Game Mechanics**: Developers will incorporate more sophisticated VR mechanics, offering richer and more varied gameplay experiences.\n\nIn conclusion, virtual reality is not just an add-on to the Hytale experience—it's a game-changer. By enhancing creativity, social interaction, and immersion, VR is setting new standards for what players can expect from a vanilla Hytale server. As technology continues to evolve, so too will the opportunities for adventure and innovation in the world of Hytale.",
  "slug": "role-of-virtual-reality-vanilla-hytale-server-experiences-2026",
  "backlinks": [],
  "category": "AUTO",
  "status": "published",
  "createdAt": "2026-02-24T10:38:06.031Z",
  "updatedAt": "2026-02-24T10:38:06.031Z"
}